{"clicked": false, "created_utc": 1539726343.0, "distinguished": null, "edited": false, "id": "9os4zv", "is_video": false, "locked": false, "num_comments": 2128, "over_18": false, "permalink": "/r/movies/comments/9os4zv/netflix_adds_7_million_subscribers_beats/", "score": 36358, "selftext": "", "stickied": false, "subreddit_id": "t5_2qh3s", "title": "Netflix Adds 7 Million Subscribers, Beats Estimates, Sends Stock Soaring 12%", "url": "https://deadline.com/2018/10/netflix-adds-7-million-subscribers-beats-estimates-1202484030/", "author_name": "BunyipPouch", "author_id": "a1s4w", "subreddit_name": "movies", "upvote_ratio": 0.89}