{"clicked": false, "created_utc": 1537274320.0, "distinguished": null, "edited": false, "id": "9gug6o", "is_video": false, "locked": false, "num_comments": 6358, "over_18": false, "permalink": "/r/movies/comments/9gug6o/captain_marvel_trailer/", "score": 42139, "selftext": "", "stickied": false, "subreddit_id": "t5_2qh3s", "title": "Captain Marvel trailer", "url": "https://youtube.com/watch?v=Z1BCujX3pw8", "author_name": "fifthdayofmay", "author_id": "hkvlm", "subreddit_name": "movies", "upvote_ratio": 0.77}