{"clicked": false, "created_utc": 1522157289.0, "distinguished": null, "edited": false, "id": "87ienr", "is_video": false, "locked": false, "num_comments": 2686, "over_18": false, "permalink": "/r/movies/comments/87ienr/banning_netflix_amazon_from_festivals_and_awards/", "score": 49915, "selftext": "", "stickied": false, "subreddit_id": "t5_2qh3s", "title": "Banning Netflix, Amazon From Festivals And Awards Is Wrong", "url": "https://www.forbes.com/sites/markhughes/2018/03/27/banning-netflix-amazon-from-festivals-and-awards-is-wrong/#6b3e382d7bf6", "author_name": "Rugby11", "author_id": "gmr5v", "subreddit_name": "movies", "upvote_ratio": 0.78}