{"clicked": false, "created_utc": 1570273318.0, "distinguished": null, "edited": false, "id": "ddlrds", "is_video": false, "locked": false, "num_comments": 2493, "over_18": false, "permalink": "/r/movies/comments/ddlrds/no_time_to_die_first_official_poster/", "score": 54657, "selftext": "", "stickied": false, "subreddit_id": "t5_2qh3s", "title": "'No Time To Die' First Official Poster", "url": "https://i.imgur.com/mGSMzUj.jpg", "author_name": "Niyazali_Haneef", "author_id": "pf45zk9", "subreddit_name": "movies", "upvote_ratio": 0.89}