{"clicked": false, "created_utc": 1558091884.0, "distinguished": null, "edited": false, "id": "bppy7f", "is_video": false, "locked": false, "num_comments": 1689, "over_18": false, "permalink": "/r/movies/comments/bppy7f/i_keep_all_my_cinema_tickets_to_stick_in_this/", "score": 71063, "selftext": "", "stickied": false, "subreddit_id": "t5_2qh3s", "title": "I keep all my cinema tickets to stick in this book and do a quick doodle with each one- I though reddit would enjoy the one from Wednesday\u2019s double bill", "url": "https://i.redd.it/skhysprl9ry21.jpg", "author_name": "neeveewood", "author_id": "11zqr1", "subreddit_name": "movies", "upvote_ratio": 0.89}