{"clicked": false, "created_utc": 1553612589.0, "distinguished": null, "edited": false, "id": "b5qrlo", "is_video": false, "locked": false, "num_comments": 1947, "over_18": false, "permalink": "/r/movies/comments/b5qrlo/new_poster_released_for_scary_stories_to_tell_in/", "score": 39908, "selftext": "", "stickied": false, "subreddit_id": "t5_2qh3s", "title": "New poster released for \u2018Scary Stories To Tell In The Dark\u2019", "url": "https://i.redd.it/ly0tscycaho21.jpg", "author_name": "thomasp003", "author_id": "8sf982v", "subreddit_name": "movies", "upvote_ratio": 0.87}