{"clicked": false, "created_utc": 1553181099.0, "distinguished": null, "edited": false, "id": "b3ro31", "is_video": false, "locked": false, "num_comments": 2854, "over_18": false, "permalink": "/r/movies/comments/b3ro31/john_wick_chapter_3_official_trailer/", "score": 40353, "selftext": "", "stickied": false, "subreddit_id": "t5_2qh3s", "title": "John Wick Chapter 3 Official Trailer", "url": "https://youtu.be/pU8-7BX9uxs", "author_name": "T-Man251", "author_id": "34eu9yn9", "subreddit_name": "movies", "upvote_ratio": 0.91}