{"clicked": false, "created_utc": 1558956440.0, "distinguished": null, "edited": false, "id": "btkw6y", "is_video": false, "locked": false, "num_comments": 2426, "over_18": false, "permalink": "/r/movies/comments/btkw6y/ridley_scott_to_direct_third_alien_prequel_movie/", "score": 30396, "selftext": "", "stickied": false, "subreddit_id": "t5_2qh3s", "title": "Ridley Scott to direct third Alien prequel movie, which is currently in the script phase", "url": "http://variety.com/2019/film/news/alien-40-anniverary-ridley-scott-1203223989/", "author_name": "magikarpcatcher", "author_id": "10sfpj", "subreddit_name": "movies", "upvote_ratio": 0.9}