{"clicked": false, "created_utc": 1549212172.0, "distinguished": null, "edited": false, "id": "amr7kt", "is_video": false, "locked": false, "num_comments": 2712, "over_18": false, "permalink": "/r/movies/comments/amr7kt/first_poster_for_documentary_hail_satan_traces/", "score": 43744, "selftext": "", "stickied": false, "subreddit_id": "t5_2qh3s", "title": "First Poster for Documentary 'Hail Satan?' - Traces the rise of The Satanic Temple, one of the most controversial religious movements in American history.", "url": "https://i.redd.it/ctzxe6z4tde21.jpg", "author_name": "BunyipPouch", "author_id": "a1s4w", "subreddit_name": "movies", "upvote_ratio": 0.72}